smqtk_relevancy/__init__.py
smqtk_relevancy/impls/__init__.py
smqtk_relevancy/impls/rank_relevancy/__init__.py
smqtk_relevancy/impls/rank_relevancy/margin_sampling.py
smqtk_relevancy/impls/rank_relevancy/random_sampling.py
smqtk_relevancy/impls/rank_relevancy/sorted_sampling.py
smqtk_relevancy/impls/rank_relevancy/wrap_classifier.py
smqtk_relevancy/impls/relevancy_index/__init__.py
smqtk_relevancy/impls/relevancy_index/classifier_wrapper.py
smqtk_relevancy/impls/relevancy_index/libsvm_hik.py
smqtk_relevancy/interfaces/__init__.py
smqtk_relevancy/interfaces/rank_relevancy.py
smqtk_relevancy/interfaces/relevancy_index.py
smqtk_relevancy/py.typed
smqtk_relevancy/utils/__init__.py
smqtk_relevancy/utils/distance_kernel.py
smqtk_relevancy-0.17.0.dist-info/entry_points.txt
smqtk_relevancy-0.17.0.dist-info/LICENSE.txt
smqtk_relevancy-0.17.0.dist-info/WHEEL
smqtk_relevancy-0.17.0.dist-info/METADATA
smqtk_relevancy-0.17.0.dist-info/RECORD
