Metadata-Version: 2.1
Name: smqtk-relevancy
Version: 0.17.0
Summary: SMQTK Relevancy
License: BSD-3-Clause
Author: Kitware, Inc.
Author-email: smqtk-developers@kitware.com
Requires-Python: >=3.6,<4.0
Classifier: License :: OSI Approved :: BSD License
Classifier: Programming Language :: Python :: 3
Classifier: Programming Language :: Python :: 3.10
Classifier: Programming Language :: Python :: 3.6
Classifier: Programming Language :: Python :: 3.7
Classifier: Programming Language :: Python :: 3.8
Classifier: Programming Language :: Python :: 3.9
Requires-Dist: numpy (>=1.19.5,<2.0.0)
Requires-Dist: smqtk-classifier (>=0.19.0)
Requires-Dist: smqtk-core (>=0.18.0)
Requires-Dist: smqtk-dataprovider (>=0.16.0)
Requires-Dist: smqtk-indexing (>=0.17.0)
